impact_parser/__init__.py
impact_parser/main.py
impact_parser/prompts.py
impact_parser-2025.12.21202313.dist-info/METADATA
impact_parser-2025.12.21202313.dist-info/WHEEL
impact_parser-2025.12.21202313.dist-info/top_level.txt
impact_parser-2025.12.21202313.dist-info/RECORD
