Metadata-Version: 2.4
Name: impact-parser
Version: 2025.12.21202313
Summary: impact-parser processes text to extract structured data on service disruptions, including affected areas, impact scope, causes, and restoration times.
Author-email: impact-parser <hi@eugene.plus>
License: MIT
Project-URL: Homepage, https://github.com/chigwell/impact-parser
Requires-Python: >=3.9
Requires-Dist: langchain-llm7>=0.0.0
Requires-Dist: llmatch-messages>=0.0.0
Requires-Dist: langchain-core>=0.3.0
